ctm/__init__.py
ctm/ctm.py
ctm/ctm_rsd.py
ctm/cosmology/__init__.py
ctm/cosmology/cosmology.py
ctm/cosmology/time_dependence.py
ctm/misc/__init__.py
ctm/misc/plotting.py
ctm/misc/progress_update.py
ctm/misc/timer.py
ctm/power_spectrum/LPT.py
ctm/power_spectrum/LPT_oneloop.py
ctm/power_spectrum/__init__.py
ctm/power_spectrum/correlation_funcs.py
ctm/power_spectrum/covariances.py
ctm/power_spectrum/covariances_oneloop.py
ctm/power_spectrum/ctm_power.py
ctm/power_spectrum/integration.py
ctm/power_spectrum/integration_rsd.py
gctm/__init__.py
gctm/gctm.py
gctm/cosmology/__init__.py
gctm/cosmology/cosmology.py
gctm/cosmology/time_dependence.py
gctm/misc/__init__.py
gctm/misc/plotting.py
gctm/misc/progress_update.py
gctm/misc/timer.py
gctm/power_spectrum/LPT.py
gctm/power_spectrum/__init__.py
gctm/power_spectrum/covariances.py
gctm/power_spectrum/gctm_power.py
gctm/power_spectrum/integration.py
cosmotm-1.11.dist-info/METADATA
cosmotm-1.11.dist-info/WHEEL
cosmotm-1.11.dist-info/top_level.txt
cosmotm-1.11.dist-info/RECORD
